keras_diagram/__init__.py
keras_diagram/diagram.py
keras_diagram/diagram_test.py
keras_diagram-1.0.5.dist-info/DESCRIPTION.rst
keras_diagram-1.0.5.dist-info/METADATA
keras_diagram-1.0.5.dist-info/RECORD
keras_diagram-1.0.5.dist-info/WHEEL
keras_diagram-1.0.5.dist-info/metadata.json
keras_diagram-1.0.5.dist-info/top_level.txt
