Metadata-Version: 2.0
Name: keras-diagram
Version: 1.0.5
Summary: Keras models as ASCII diagrams
Home-page: http://github.com/brianlow/keras_diagram
Author: Brian Low
Author-email: brian.low22@gmail.com
License: MIT
Keywords: keras ascii diagram model
Platform: UNKNOWN
